deadman/__init__.py
deadman/cli.py
deadman-0.1.10.dist-info/METADATA
deadman-0.1.10.dist-info/WHEEL
deadman-0.1.10.dist-info/entry_points.txt
deadman-0.1.10.dist-info/top_level.txt
deadman-0.1.10.dist-info/RECORD
